aws_secrets/__init__.py
aws_secrets/credential.py
aws_secrets-0.1.10.dist-info/METADATA
aws_secrets-0.1.10.dist-info/WHEEL
aws_secrets-0.1.10.dist-info/licenses/LICENSE.txt
aws_secrets-0.1.10.dist-info/RECORD
