Metadata-Version: 2.1
Name: aws_secrets
Version: 0.1.10
Summary: Python library for resolving secrets from AWS Secrets Manager
Project-URL: Homepage, https://github.com/davidcroda/aws_secrets
Project-URL: Bug Tracker, https://github.com/davidcroda/aws_secrets/issues
Author-email: David Roda <davidcroda@gmail.com>
License-File: LICENSE.txt
Classifier: License :: OSI Approved :: MIT License
Classifier: Operating System :: OS Independent
Classifier: Programming Language :: Python :: 3
Requires-Python: >=3.7
Requires-Dist: boto3
